weblog/__init__.py
weblog/admin.py
weblog/apps.py
weblog/feeds.py
weblog/models.py
weblog/tests.py
weblog/urls.py
weblog/views.py
weblog/locale/es/LC_MESSAGES/django.mo
weblog/locale/es/LC_MESSAGES/django.po
weblog/locale/ru/LC_MESSAGES/django.mo
weblog/locale/ru/LC_MESSAGES/django.po
weblog/migrations/0001_initial.py
weblog/migrations/0002_auto_20180113_1606.py
weblog/migrations/0003_auto_20180119_0156.py
weblog/migrations/0004_auto_20180119_0156.py
weblog/migrations/0005_auto_20180119_0231.py
weblog/migrations/0006_auto_20180121_1002.py
weblog/migrations/0007_auto_20180122_1943.py
weblog/migrations/0008_auto_20180329_1316.py
weblog/migrations/0008_auto_20180531_0329.py
weblog/migrations/0009_merge_20190104_2123.py
weblog/migrations/0010_auto_20190110_1901.py
weblog/migrations/__init__.py
weblog/static/weblog/css/weblog.css
weblog/static/weblog/js/weblog.js
weblog/templates/weblog_base.html
weblog/templates/weblog_base_old.html
weblog/templates/weblog/.index.html.swp
weblog/templates/weblog/.post.html.swp
weblog/templates/weblog/.weblog.html.swp
weblog/templates/weblog/index.html
weblog/templates/weblog/nxtpage.html
weblog/templates/weblog/post.html
weblog/templates/weblog/sidebar_archive.html
weblog/templates/weblog/sidebar_categories.html
weblog/templates/weblog/weblog.html
weblog/templatetags/__init__.py
weblog/templatetags/weblog_extras.py
w3blog-0.5.2.dist-info/LICENSE
w3blog-0.5.2.dist-info/METADATA
w3blog-0.5.2.dist-info/WHEEL
w3blog-0.5.2.dist-info/top_level.txt
w3blog-0.5.2.dist-info/RECORD
